neonpy/__init__.py
neonpy/memoize.py
neonpy/normalize.py
neonpy/util/__init__.py
tests/__init__.py
tests/basic_tests.py
neonpy-0.0.1.dist-info/METADATA
neonpy-0.0.1.dist-info/WHEEL
neonpy-0.0.1.dist-info/top_level.txt
neonpy-0.0.1.dist-info/RECORD
