Metadata-Version: 2.1
Name: neonpy
Version: 0.0.1
Summary: add a little neon to your python
Home-page: https://github.com/mrmechko/neon
Author: Rik Bose
Author-email: rbose@cs.rochester.edu
License: UNKNOWN
Platform: UNKNOWN
Classifier: Programming Language :: Python :: 3
Classifier: License :: OSI Approved :: GNU General Public License v2 or later (GPLv2+)
Classifier: Operating System :: OS Independent
